[[{"py/object": "class_definitions.PDFTerm", "entity_id": 4575011336, "facet": "method", "id": 4578794968, "page_number": "0", "pdf_words": [{"py/object": "class_definitions.PDFWord", "bdr": "0.34308,0.36919,0.38053,0.37931", "facet": "method", "id": 4578795248, "page_number": "0", "pdf_term_id": 4578794968, "text": "trec", "type": "PDFWord", "word_id": "w-1-0-1-34"}], "sent_id": "s-1-0-1-0", "type": "PDFTerm"}], [{"py/object": "class_definitions.PDFTerm", "entity_id": 4575013352, "facet": "method", "id": 4575120016, "page_number": "1", "pdf_words": [{"py/object": "class_definitions.PDFWord", "bdr": "0.62105,0.13630,0.66256,0.14642", "facet": "method", "id": 4575120296, "page_number": "1", "pdf_term_id": 4575120016, "text": "html", "type": "PDFWord", "word_id": "w-1-0-4-39"}], "sent_id": "s-1-0-4-0", "type": "PDFTerm"}, {"py/object": "class_definitions.PDFTerm", "entity_id": 4575013352, "facet": "method", "id": 4575120352, "page_number": "1", "pdf_words": [{"py/object": "class_definitions.PDFWord", "bdr": "0.51767,0.48305,0.55917,0.49317", "facet": "method", "id": 4575120408, "page_number": "1", "pdf_term_id": 4575120352, "text": "html", "type": "PDFWord", "word_id": "w-1-0-4-192"}], "sent_id": "s-1-0-4-6", "type": "PDFTerm"}, {"py/object": "class_definitions.PDFTerm", "entity_id": 4575013352, "facet": "method", "id": 4575120464, "page_number": "1", "pdf_words": [{"py/object": "class_definitions.PDFWord", "bdr": "0.65845,0.74738,0.69995,0.75750", "facet": "method", "id": 4575120520, "page_number": "1", "pdf_term_id": 4575120464, "text": "html", "type": "PDFWord", "word_id": "w-1-0-4-400"}], "sent_id": "s-1-0-4-14", "type": "PDFTerm"}], [{"py/object": "class_definitions.PDFTerm", "entity_id": 4575011000, "facet": "method", "id": 4578792616, "page_number": "3", "pdf_words": [{"py/object": "class_definitions.PDFWord", "bdr": "0.64296,0.30618,0.68689,0.31630", "facet": "method", "id": 4578793008, "page_number": "3", "pdf_term_id": 4578792616, "text": "jaccard", "type": "PDFWord", "word_id": "w-1-0-9-26"}], "sent_id": "s-1-0-9-1", "type": "PDFTerm"}, {"py/object": "class_definitions.PDFTerm", "entity_id": 4575011000, "facet": "method", "id": 4578793064, "page_number": "3", "pdf_words": [{"py/object": "class_definitions.PDFWord", "bdr": "0.57948,0.42439,0.62340,0.43451", "facet": "method", "id": 4578793120, "page_number": "3", "pdf_term_id": 4578793064, "text": "jaccard", "type": "PDFWord", "word_id": "w-1-0-9-137"}], "sent_id": "s-1-0-9-5", "type": "PDFTerm"}, {"py/object": "class_definitions.PDFTerm", "entity_id": 4575011000, "facet": "method", "id": 4578792952, "page_number": "3", "pdf_words": [{"py/object": "class_definitions.PDFWord", "bdr": "0.66336,0.45080,0.70728,0.46092", "facet": "method", "id": 4578793232, "page_number": "3", "pdf_term_id": 4578792952, "text": "jaccard", "type": "PDFWord", "word_id": "w-1-0-9-167"}], "sent_id": "s-1-0-9-5", "type": "PDFTerm"}, {"py/object": "class_definitions.PDFTerm", "entity_id": 4575013352, "facet": "method", "id": 4575120240, "page_number": "3", "pdf_words": [{"py/object": "class_definitions.PDFWord", "bdr": "0.19129,0.35801,0.23280,0.36813", "facet": "method", "id": 4575120632, "page_number": "3", "pdf_term_id": 4575120240, "text": "html", "type": "PDFWord", "word_id": "w-1-0-8-49"}], "sent_id": "s-1-0-8-0", "type": "PDFTerm"}, {"py/object": "class_definitions.PDFTerm", "entity_id": 4575013352, "facet": "method", "id": 4575120576, "page_number": "3", "pdf_words": [{"py/object": "class_definitions.PDFWord", "bdr": "0.59986,0.70387,0.64136,0.71399", "facet": "method", "id": 4575120744, "page_number": "3", "pdf_term_id": 4575120576, "text": "html", "type": "PDFWord", "word_id": "w-1-0-9-363"}], "sent_id": "s-1-0-9-10", "type": "PDFTerm"}, {"py/object": "class_definitions.PDFTerm", "entity_id": 4575013352, "facet": "method", "id": 4575120688, "page_number": "3", "pdf_words": [{"py/object": "class_definitions.PDFWord", "bdr": "0.72864,0.89862,0.76380,0.90736", "facet": "method", "id": 4575120856, "page_number": "3", "pdf_term_id": 4575120688, "text": "html", "type": "PDFWord", "word_id": "w-1-0-9-546"}], "sent_id": "s-1-0-9-15", "type": "PDFTerm"}], [{"py/object": "class_definitions.PDFTerm", "entity_id": 4575011000, "facet": "method", "id": 4578793176, "page_number": "5", "pdf_words": [{"py/object": "class_definitions.PDFWord", "bdr": "0.61987,0.43996,0.66380,0.45009", "facet": "method", "id": 4578793344, "page_number": "5", "pdf_term_id": 4578793176, "text": "jaccard", "type": "PDFWord", "word_id": "w-1-0-13-311"}], "sent_id": "s-1-0-13-12", "type": "PDFTerm"}, {"py/object": "class_definitions.PDFTerm", "entity_id": 4575011224, "facet": "method", "id": 4578794632, "page_number": "5", "pdf_words": [{"py/object": "class_definitions.PDFWord", "bdr": "0.56162,0.21778,0.63829,0.23135", "facet": "method", "id": 4578794800, "page_number": "5", "pdf_term_id": 4578794632, "text": "resource", "type": "PDFWord", "word_id": "w-1-0-13-118"}, {"py/object": "class_definitions.PDFWord", "bdr": "0.64318,0.21778,0.71805,0.23135", "facet": "method", "id": 4578794856, "page_number": "5", "pdf_term_id": 4578794632, "text": "selection", "type": "PDFWord", "word_id": "w-1-0-13-119"}, {"py/object": "class_definitions.PDFWord", "bdr": "0.72294,0.21778,0.76240,0.23135", "facet": "method", "id": 4578794912, "page_number": "5", "pdf_term_id": 4578794632, "text": "task", "type": "PDFWord", "word_id": "w-1-0-13-120"}], "sent_id": "s-1-0-13-4", "type": "PDFTerm"}], [{"py/object": "class_definitions.PDFTerm", "entity_id": 4575010888, "facet": "method", "id": 4578792560, "page_number": "6", "pdf_words": [{"py/object": "class_definitions.PDFWord", "bdr": "0.19779,0.22530,0.22627,0.23542", "facet": "method", "id": 4578792672, "page_number": "6", "pdf_term_id": 4578792560, "text": "indri", "type": "PDFWord", "word_id": "w-1-0-14-121"}], "sent_id": "s-1-0-14-5", "type": "PDFTerm"}, {"py/object": "class_definitions.PDFTerm", "entity_id": 4575011000, "facet": "method", "id": 4578793400, "page_number": "6", "pdf_words": [{"py/object": "class_definitions.PDFWord", "bdr": "0.38523,0.28178,0.42916,0.29190", "facet": "method", "id": 4578793456, "page_number": "6", "pdf_term_id": 4578793400, "text": "jaccard", "type": "PDFWord", "word_id": "w-1-0-14-171"}], "sent_id": "s-1-0-14-8", "type": "PDFTerm"}, {"py/object": "class_definitions.PDFTerm", "entity_id": 4575011000, "facet": "method", "id": 4578793288, "page_number": "6", "pdf_words": [{"py/object": "class_definitions.PDFWord", "bdr": "0.08791,0.56279,0.13183,0.57291", "facet": "method", "id": 4578793568, "page_number": "6", "pdf_term_id": 4578793288, "text": "jaccard", "type": "PDFWord", "word_id": "w-1-0-14-440"}], "sent_id": "s-1-0-14-20", "type": "PDFTerm"}, {"py/object": "class_definitions.PDFTerm", "entity_id": 4575011000, "facet": "method", "id": 4578793624, "page_number": "6", "pdf_words": [{"py/object": "class_definitions.PDFWord", "bdr": "0.20103,0.72657,0.24495,0.73669", "facet": "method", "id": 4578793680, "page_number": "6", "pdf_term_id": 4578793624, "text": "jaccard", "type": "PDFWord", "word_id": "w-1-0-14-628"}], "sent_id": "s-1-0-14-26", "type": "PDFTerm"}, {"py/object": "class_definitions.PDFTerm", "entity_id": 4575011224, "facet": "method", "id": 4578794744, "page_number": "6", "pdf_words": [{"py/object": "class_definitions.PDFWord", "bdr": "0.14986,0.87160,0.19949,0.88172", "facet": "method", "id": 4578795024, "page_number": "6", "pdf_term_id": 4578794744, "text": "resource", "type": "PDFWord", "word_id": "w-1-0-14-715"}, {"py/object": "class_definitions.PDFWord", "bdr": "0.20413,0.87160,0.25622,0.88172", "facet": "method", "id": 4578795080, "page_number": "6", "pdf_term_id": 4578794744, "text": "selection", "type": "PDFWord", "word_id": "w-1-0-14-716"}, {"py/object": "class_definitions.PDFWord", "bdr": "0.26084,0.87160,0.28445,0.88172", "facet": "method", "id": 4578795136, "page_number": "6", "pdf_term_id": 4578794744, "text": "task", "type": "PDFWord", "word_id": "w-1-0-14-717"}], "sent_id": "s-1-0-14-29", "type": "PDFTerm"}, {"py/object": "class_definitions.PDFTerm", "entity_id": 4575012120, "facet": "method", "id": 4575099312, "page_number": "6", "pdf_words": [{"py/object": "class_definitions.PDFWord", "bdr": "0.14610,0.85368,0.21207,0.86560", "facet": "method", "id": 4575099592, "page_number": "6", "pdf_term_id": 4575099312, "text": "resource", "type": "PDFWord", "word_id": "w-1-0-14-711"}, {"py/object": "class_definitions.PDFWord", "bdr": "0.21655,0.85368,0.28219,0.86560", "facet": "method", "id": 4575099648, "page_number": "6", "pdf_term_id": 4575099312, "text": "selection", "type": "PDFWord", "word_id": "w-1-0-14-712"}, {"py/object": "class_definitions.PDFWord", "bdr": "0.10256,0.87160,0.12269,0.88172", "facet": "method", "id": 4575099704, "page_number": "6", "pdf_term_id": 4575099312, "text": "for", "type": "PDFWord", "word_id": "w-1-0-14-713"}], "sent_id": "s-1-0-14-29", "type": "PDFTerm"}], [{"py/object": "class_definitions.PDFTerm", "entity_id": 4575011168, "facet": "method", "id": 4578793512, "page_number": "7", "pdf_words": [{"py/object": "class_definitions.PDFWord", "bdr": "0.58336,0.19831,0.64381,0.20843", "facet": "method", "id": 4578793792, "page_number": "7", "pdf_term_id": 4578793512, "text": "wikipedia", "type": "PDFWord", "word_id": "w-1-0-17-69"}], "sent_id": "s-1-0-17-3", "type": "PDFTerm"}, {"py/object": "class_definitions.PDFTerm", "entity_id": 4575011336, "facet": "method", "id": 4578795304, "page_number": "7", "pdf_words": [{"py/object": "class_definitions.PDFWord", "bdr": "0.76700,0.15868,0.80444,0.16880", "facet": "method", "id": 4578795360, "page_number": "7", "pdf_term_id": 4578795304, "text": "trec", "type": "PDFWord", "word_id": "w-1-0-17-40"}], "sent_id": "s-1-0-17-3", "type": "PDFTerm"}, {"py/object": "class_definitions.PDFTerm", "entity_id": 4575011336, "facet": "method", "id": 4578795192, "page_number": "7", "pdf_words": [{"py/object": "class_definitions.PDFWord", "bdr": "0.51767,0.43595,0.55511,0.44607", "facet": "method", "id": 4578795472, "page_number": "7", "pdf_term_id": 4578795192, "text": "trec", "type": "PDFWord", "word_id": "w-1-0-17-241"}], "sent_id": "s-1-0-17-10", "type": "PDFTerm"}], [{"py/object": "class_definitions.PDFTerm", "entity_id": 4575011168, "facet": "method", "id": 4578793736, "page_number": "8", "pdf_words": [{"py/object": "class_definitions.PDFWord", "bdr": "0.30257,0.19184,0.36302,0.20197", "facet": "method", "id": 4578793904, "page_number": "8", "pdf_term_id": 4578793736, "text": "wikipedia", "type": "PDFWord", "word_id": "w-1-0-18-101"}], "sent_id": "s-1-0-18-3", "type": "PDFTerm"}, {"py/object": "class_definitions.PDFTerm", "entity_id": 4575011168, "facet": "method", "id": 4578793848, "page_number": "8", "pdf_words": [{"py/object": "class_definitions.PDFWord", "bdr": "0.41815,0.21826,0.47860,0.22838", "facet": "method", "id": 4578794016, "page_number": "8", "pdf_term_id": 4578793848, "text": "wikipedia", "type": "PDFWord", "word_id": "w-1-0-18-133"}], "sent_id": "s-1-0-18-4", "type": "PDFTerm"}, {"py/object": "class_definitions.PDFTerm", "entity_id": 4575011168, "facet": "method", "id": 4578793960, "page_number": "8", "pdf_words": [{"py/object": "class_definitions.PDFWord", "bdr": "0.39602,0.24468,0.45647,0.25480", "facet": "method", "id": 4578794128, "page_number": "8", "pdf_term_id": 4578793960, "text": "wikipedia", "type": "PDFWord", "word_id": "w-1-0-18-158"}], "sent_id": "s-1-0-18-4", "type": "PDFTerm"}, {"py/object": "class_definitions.PDFTerm", "entity_id": 4575011168, "facet": "method", "id": 4578794184, "page_number": "8", "pdf_words": [{"py/object": "class_definitions.PDFWord", "bdr": "0.41815,0.29765,0.47860,0.30777", "facet": "method", "id": 4578794240, "page_number": "8", "pdf_term_id": 4578794184, "text": "wikipedia", "type": "PDFWord", "word_id": "w-1-0-18-189"}], "sent_id": "s-1-0-18-6", "type": "PDFTerm"}, {"py/object": "class_definitions.PDFTerm", "entity_id": 4575011168, "facet": "method", "id": 4578794072, "page_number": "8", "pdf_words": [{"py/object": "class_definitions.PDFWord", "bdr": "0.15741,0.36383,0.21786,0.37395", "facet": "method", "id": 4578794352, "page_number": "8", "pdf_term_id": 4578794072, "text": "wikipedia", "type": "PDFWord", "word_id": "w-1-0-18-217"}], "sent_id": "s-1-0-18-7", "type": "PDFTerm"}, {"py/object": "class_definitions.PDFTerm", "entity_id": 4575011168, "facet": "method", "id": 4578794296, "page_number": "8", "pdf_words": [{"py/object": "class_definitions.PDFWord", "bdr": "0.26770,0.54902,0.32815,0.55915", "facet": "method", "id": 4578794464, "page_number": "8", "pdf_term_id": 4578794296, "text": "wikipedia", "type": "PDFWord", "word_id": "w-1-0-18-344"}], "sent_id": "s-1-0-18-12", "type": "PDFTerm"}, {"py/object": "class_definitions.PDFTerm", "entity_id": 4572242552, "facet": "method", "id": 4575097576, "page_number": "8", "pdf_words": [{"py/object": "class_definitions.PDFWord", "bdr": "0.26800,0.62827,0.31763,0.63839", "facet": "method", "id": 4575097632, "page_number": "8", "pdf_term_id": 4575097576, "text": "random", "type": "PDFWord", "word_id": "w-1-0-18-408"}, {"py/object": "class_definitions.PDFWord", "bdr": "0.32248,0.62827,0.35584,0.63839", "facet": "method", "id": 4575097688, "page_number": "8", "pdf_term_id": 4575097576, "text": "forest", "type": "PDFWord", "word_id": "w-1-0-18-409"}], "sent_id": "s-1-0-18-16", "type": "PDFTerm"}, {"py/object": "class_definitions.PDFTerm", "entity_id": 4575011448, "facet": "method", "id": 4575097744, "page_number": "8", "pdf_words": [{"py/object": "class_definitions.PDFWord", "bdr": "0.13142,0.72101,0.17536,0.73113", "facet": "method", "id": 4575097800, "page_number": "8", "pdf_term_id": 4575097744, "text": "feature", "type": "PDFWord", "word_id": "w-1-0-18-452"}, {"py/object": "class_definitions.PDFWord", "bdr": "0.18144,0.72101,0.23272,0.73113", "facet": "method", "id": 4575097856, "page_number": "8", "pdf_term_id": 4575097744, "text": "analysis", "type": "PDFWord", "word_id": "w-1-0-18-453"}, {"py/object": "class_definitions.PDFWord", "bdr": "0.23880,0.72101,0.25995,0.73113", "facet": "method", "id": 4575097912, "page_number": "8", "pdf_term_id": 4575097744, "text": "and", "type": "PDFWord", "word_id": "w-1-0-18-454"}], "sent_id": "s-1-0-18-18", "type": "PDFTerm"}, {"py/object": "class_definitions.PDFTerm", "entity_id": 4575011616, "facet": "method", "id": 4575097240, "page_number": "8", "pdf_words": [{"py/object": "class_definitions.PDFWord", "bdr": "0.16211,0.41680,0.21851,0.42693", "facet": "method", "id": 4575098024, "page_number": "8", "pdf_term_id": 4575097240, "text": "wikilink", "type": "PDFWord", "word_id": "w-1-0-18-247"}], "sent_id": "s-1-0-18-9", "type": "PDFTerm"}], [{"py/object": "class_definitions.PDFTerm", "entity_id": 4575011336, "facet": "method", "id": 4578795416, "page_number": "9", "pdf_words": [{"py/object": "class_definitions.PDFWord", "bdr": "0.55910,0.69682,0.59655,0.70695", "facet": "method", "id": 4575096960, "page_number": "9", "pdf_term_id": 4578795416, "text": "trec", "type": "PDFWord", "word_id": "w-1-0-22-117"}], "sent_id": "s-1-0-22-7", "type": "PDFTerm"}], [{"py/object": "class_definitions.PDFTerm", "entity_id": 4575010944, "facet": "method", "id": 4578792728, "page_number": "10", "pdf_words": [{"py/object": "class_definitions.PDFWord", "bdr": "0.21994,0.54872,0.27311,0.56229", "facet": "method", "id": 4578792784, "page_number": "10", "pdf_term_id": 4578792728, "text": "model", "type": "PDFWord", "word_id": "w-1-0-23-435"}, {"py/object": "class_definitions.PDFWord", "bdr": "0.10256,0.56782,0.15140,0.57794", "facet": "method", "id": 4578792840, "page_number": "10", "pdf_term_id": 4578792728, "text": "existing", "type": "PDFWord", "word_id": "w-1-0-23-436"}, {"py/object": "class_definitions.PDFWord", "bdr": "0.15499,0.56782,0.18495,0.57794", "facet": "method", "id": 4578792896, "page_number": "10", "pdf_term_id": 4578792728, "text": "work", "type": "PDFWord", "word_id": "w-1-0-23-437"}], "sent_id": "s-1-0-23-8", "type": "PDFTerm"}, {"py/object": "class_definitions.PDFTerm", "entity_id": 4575011336, "facet": "method", "id": 4575096904, "page_number": "10", "pdf_words": [{"py/object": "class_definitions.PDFWord", "bdr": "0.32585,0.84519,0.36330,0.85531", "facet": "method", "id": 4575097072, "page_number": "10", "pdf_term_id": 4575096904, "text": "trec", "type": "PDFWord", "word_id": "w-1-0-23-677"}], "sent_id": "s-1-0-23-15", "type": "PDFTerm"}, {"py/object": "class_definitions.PDFTerm", "entity_id": 4575011952, "facet": "method", "id": 4575098080, "page_number": "10", "pdf_words": [{"py/object": "class_definitions.PDFWord", "bdr": "0.23730,0.63386,0.26823,0.64398", "facet": "method", "id": 4575098136, "page_number": "10", "pdf_term_id": 4575098080, "text": "croft", "type": "PDFWord", "word_id": "w-1-0-23-498"}], "sent_id": "s-1-0-23-10", "type": "PDFTerm"}, {"py/object": "class_definitions.PDFTerm", "entity_id": 4575011952, "facet": "method", "id": 4575098192, "page_number": "10", "pdf_words": [{"py/object": "class_definitions.PDFWord", "bdr": "0.59082,0.26090,0.62175,0.27102", "facet": "method", "id": 4575098248, "page_number": "10", "pdf_term_id": 4575098192, "text": "croft", "type": "PDFWord", "word_id": "w-1-0-24-177"}], "sent_id": "s-1-0-24-3", "type": "PDFTerm"}], [{"py/object": "class_definitions.PDFTerm", "entity_id": 4575011168, "facet": "method", "id": 4578794408, "page_number": "12", "pdf_words": [{"py/object": "class_definitions.PDFWord", "bdr": "0.65162,0.58191,0.71207,0.59203", "facet": "method", "id": 4578794576, "page_number": "12", "pdf_term_id": 4578794408, "text": "wikipedia", "type": "PDFWord", "word_id": "w-1-0-30-445"}], "sent_id": "s-1-0-30-36", "type": "PDFTerm"}, {"py/object": "class_definitions.PDFTerm", "entity_id": 4575011168, "facet": "method", "id": 4578794520, "page_number": "12", "pdf_words": [{"py/object": "class_definitions.PDFWord", "bdr": "0.61854,0.67927,0.67899,0.68939", "facet": "method", "id": 4578794688, "page_number": "12", "pdf_term_id": 4578794520, "text": "wikipedia", "type": "PDFWord", "word_id": "w-1-0-30-530"}], "sent_id": "s-1-0-30-44", "type": "PDFTerm"}, {"py/object": "class_definitions.PDFTerm", "entity_id": 4575011336, "facet": "method", "id": 4575097128, "page_number": "12", "pdf_words": [{"py/object": "class_definitions.PDFWord", "bdr": "0.25632,0.08604,0.29377,0.09616", "facet": "method", "id": 4575097184, "page_number": "12", "pdf_term_id": 4575097128, "text": "trec", "type": "PDFWord", "word_id": "w-1-0-29-27"}], "sent_id": "s-1-0-29-1", "type": "PDFTerm"}, {"py/object": "class_definitions.PDFTerm", "entity_id": 4575011336, "facet": "method", "id": 4575097016, "page_number": "12", "pdf_words": [{"py/object": "class_definitions.PDFWord", "bdr": "0.17373,0.09936,0.20955,0.10911", "facet": "method", "id": 4575097296, "page_number": "12", "pdf_term_id": 4575097016, "text": "trec", "type": "PDFWord", "word_id": "w-1-0-29-37"}], "sent_id": "s-1-0-29-2", "type": "PDFTerm"}, {"py/object": "class_definitions.PDFTerm", "entity_id": 4575011336, "facet": "method", "id": 4575097352, "page_number": "12", "pdf_words": [{"py/object": "class_definitions.PDFWord", "bdr": "0.34132,0.88481,0.37877,0.89493", "facet": "method", "id": 4575097408, "page_number": "12", "pdf_term_id": 4575097352, "text": "trec", "type": "PDFWord", "word_id": "w-1-0-29-642"}], "sent_id": "s-1-0-29-52", "type": "PDFTerm"}, {"py/object": "class_definitions.PDFTerm", "entity_id": 4575011336, "facet": "method", "id": 4575097464, "page_number": "12", "pdf_words": [{"py/object": "class_definitions.PDFWord", "bdr": "0.24007,0.89813,0.27589,0.90788", "facet": "method", "id": 4575097520, "page_number": "12", "pdf_term_id": 4575097464, "text": "trec", "type": "PDFWord", "word_id": "w-1-0-29-649"}], "sent_id": "s-1-0-29-53", "type": "PDFTerm"}, {"py/object": "class_definitions.PDFTerm", "entity_id": 4575011952, "facet": "method", "id": 4575097968, "page_number": "12", "pdf_words": [{"py/object": "class_definitions.PDFWord", "bdr": "0.28811,0.27913,0.31904,0.28925", "facet": "method", "id": 4575098360, "page_number": "12", "pdf_term_id": 4575097968, "text": "croft", "type": "PDFWord", "word_id": "w-1-0-29-163"}], "sent_id": "s-1-0-29-13", "type": "PDFTerm"}, {"py/object": "class_definitions.PDFTerm", "entity_id": 4575011952, "facet": "method", "id": 4575098416, "page_number": "12", "pdf_words": [{"py/object": "class_definitions.PDFWord", "bdr": "0.15537,0.42394,0.18630,0.43407", "facet": "method", "id": 4575098472, "page_number": "12", "pdf_term_id": 4575098416, "text": "croft", "type": "PDFWord", "word_id": "w-1-0-29-275"}], "sent_id": "s-1-0-29-22", "type": "PDFTerm"}, {"py/object": "class_definitions.PDFTerm", "entity_id": 4575011952, "facet": "method", "id": 4575098528, "page_number": "12", "pdf_words": [{"py/object": "class_definitions.PDFWord", "bdr": "0.68366,0.28982,0.71459,0.29994", "facet": "method", "id": 4575098584, "page_number": "12", "pdf_term_id": 4575098528, "text": "croft", "type": "PDFWord", "word_id": "w-1-0-30-205"}], "sent_id": "s-1-0-30-16", "type": "PDFTerm"}]]
